{
    "Отрасли": {
        "Как цифровизация влияет на охваты в уличной рекламе": "https://www.rbc.ru/industries/news/66d5e09e9a794741c6a51d7e?utm_source=rbc&utm_medium=main&utm_campaign=889866-66d5e09e9a794741c6a51d7e&from=newsfeed",
        "Как фундаменты небоскребов и тоннели метро защищают от подземных вод": "https://www.rbc.ru/industries/news/66c5c4289a7947532dc5bad3?utm_source=rbc&utm_medium=main&utm_campaign=895321-66c5c4289a7947532dc5bad3&from=newsfeed"
    },
    "Спорт": {
        "Кто из заложников школы в Беслане стал успешным спортсменом": "https://www.rbc.ru/sport/03/09/2024/66d6b6989a7947833233c550?from=newsfeed",
        "Участницу Олимпиады-2024 облил бензином и поджег ее бойфренд": "https://www.rbc.ru/sport/03/09/2024/66d6d25c9a7947169d4737cf?from=newsfeed"
    },
    "Политика": {
        "Минобороны сообщило о сбитом МиГ-29 ВСУ": "https://www.rbc.ru/rbcfreenews/66d6d5519a79473c69723f86?from=newsfeed",
        "Ангола предложила АЛРОСЕ решить проблему санкций в алмазодобыче": "https://www.rbc.ru/rbcfreenews/66d6d0449a794755a20d46c4?from=newsfeed",
        "МИД счел реваншизмом предложение Тайваня о Дальнем Востоке": "https://www.rbc.ru/politics/03/09/2024/66d6cbdb9a7947d73c1ba6f6?from=newsfeed",
        "«Интерфакс» сообщил, что Юдаеву выдвинут в МВФ от России": "https://www.rbc.ru/politics/03/09/2024/66d6ccf49a7947f327e93af3?from=newsfeed",
        "США и Британия сделают договор в области ядерного оружия бессрочным": "https://www.rbc.ru/rbcfreenews/66d6c6f09a794751b1dfa9b6?from=newsfeed",
        "Нападение ВСУ на Курскую область. Главное": "https://www.rbc.ru/politics/07/08/2024/66b34e289a7947b960522eb6?from=newsfeed"
    },
    "Общество": {
        "Что показали на Восточном экономическом форуме": "https://www.rbc.ru/photoreport/03/09/2024/66d6b3799a7947486f0f4b9c?from=newsfeed",
        "В Центр временного содержания мигрантов в Москве пришли с обысками": "https://www.rbc.ru/society/03/09/2024/66d6d3179a79476904715275?from=newsfeed"
    },
    "Крипто": {
        "Эксперты спрогнозировали падение цены биткоина после снижения ставки ФРС": "https://www.rbc.ru/crypto/news/66d6c89d9a794722ec6d7377?from=newsfeed"
    },
    "Национальные проекты": {
        "Какие барьеры преодолевают малые технологические компании в регионах": "https://www.rbc.ru/opinions/business/03/09/2024/66d07f659a7947cdcdc81d58?from=newsfeed"
    }
}