[
    {
        "Наименование": "Смартфон Apple iPhone 15 Pro Max 256GB Natural Titanium (Натуральный титан) nano-Sim + eSim",
        "Производитель:": "Apple",
        "Гарантия": "12 месяцев",
        "Объем памяти": "256GB",
        "P/N": "MU6R3 ",
        "Параметры SIM": "nano-Sim + eSim",
        "Комплектация": "кабель",
        "price": "2760",
        "article": "A15PM-256-NTM"
    },
    {
        "Наименование": "Смартфон Apple iPhone 15 Pro Max 256GB Natural Titanium (Натуральный титан) nano-Sim + eSim",
        "Производитель:": "Apple",
        "Гарантия": "12 месяцев",
        "Объем памяти": "256GB",
        "P/N": "MU6R3 ",
        "Параметры SIM": "nano-Sim + eSim",
        "Комплектация": "кабель",
        "price": "111950",
        "article": "A15PM-256-NTM"
    },
    {
        "Наименование": "Смартфон Apple iPhone 15 Pro Max 256GB Natural Titanium (Натуральный титан) nano-Sim + eSim",
        "Производитель:": "Apple",
        "Гарантия": "12 месяцев",
        "Объем памяти": "256GB",
        "P/N": "MU6R3 ",
        "Параметры SIM": "nano-Sim + eSim",
        "Комплектация": "кабель",
        "price": "88573",
        "article": "A15PM-256-NTM"
    },
    {
        "Наименование": "Смартфон Apple iPhone 15 Pro Max 256GB Natural Titanium (Натуральный титан) nano-Sim + eSim",
        "Производитель:": "Apple",
        "Гарантия": "12 месяцев",
        "Объем памяти": "256GB",
        "P/N": "MU6R3 ",
        "Параметры SIM": "nano-Sim + eSim",
        "Комплектация": "кабель",
        "price": "111950",
        "article": "A15PM-256-NTM"
    },
    {
        "Наименование": "Смартфон Apple iPhone 15 Pro Max 256GB Natural Titanium (Натуральный титан) nano-Sim + eSim",
        "Производитель:": "Apple",
        "Гарантия": "12 месяцев",
        "Объем памяти": "256GB",
        "P/N": "MU6R3 ",
        "Параметры SIM": "nano-Sim + eSim",
        "Комплектация": "кабель",
        "price": "13121",
        "article": "A15PM-256-NTM"
    }
]